MANIFEST.in
README.md
pyproject.toml
setup.cfg
setup.py
./src/dejavu_gi/dejavu_api_impl.cpp
./src/dejavu_gi/invariant.cpp
./src/dejavu_gi/naurng.cpp
./src/dejavu_gi/parser.cpp
./src/dejavu_gi/refinement.cpp
./src/dejavu_gi/schreier_sequential.cpp
./src/dejavu_gi/schreier_shared.cpp
./src/dejavu_gi/utility.cpp
dejavu-pip-master/src/dejavu_gi/bench.cpp
dejavu-pip-master/src/dejavu_gi/bench_iso.cpp
dejavu-pip-master/src/dejavu_gi/bfs.h
dejavu-pip-master/src/dejavu_gi/bijection.h
dejavu-pip-master/src/dejavu_gi/coloring.h
dejavu-pip-master/src/dejavu_gi/concurrentqueue.h
dejavu-pip-master/src/dejavu_gi/configuration.h
dejavu-pip-master/src/dejavu_gi/dejavu_api.cpp
dejavu-pip-master/src/dejavu_gi/dejavu_api.h
dejavu-pip-master/src/dejavu_gi/dejavu_api_impl.cpp
dejavu-pip-master/src/dejavu_gi/dejavu_api_python.cpp
dejavu-pip-master/src/dejavu_gi/dejavu_auto.cpp
dejavu-pip-master/src/dejavu_gi/dejavu_auto.h
dejavu-pip-master/src/dejavu_gi/dejavu_iso.cpp
dejavu-pip-master/src/dejavu_gi/dejavu_iso.h
dejavu-pip-master/src/dejavu_gi/group_shared.h
dejavu-pip-master/src/dejavu_gi/invariant.cpp
dejavu-pip-master/src/dejavu_gi/invariant.h
dejavu-pip-master/src/dejavu_gi/naudefs.h
dejavu-pip-master/src/dejavu_gi/naurng.cpp
dejavu-pip-master/src/dejavu_gi/naurng.h
dejavu-pip-master/src/dejavu_gi/parser.cpp
dejavu-pip-master/src/dejavu_gi/parser.h
dejavu-pip-master/src/dejavu_gi/preproc.h
dejavu-pip-master/src/dejavu_gi/refinement.cpp
dejavu-pip-master/src/dejavu_gi/refinement.h
dejavu-pip-master/src/dejavu_gi/schreier_sequential.cpp
dejavu-pip-master/src/dejavu_gi/schreier_sequential.h
dejavu-pip-master/src/dejavu_gi/schreier_shared.cpp
dejavu-pip-master/src/dejavu_gi/schreier_shared.h
dejavu-pip-master/src/dejavu_gi/selector.h
dejavu-pip-master/src/dejavu_gi/sgraph.h
dejavu-pip-master/src/dejavu_gi/utility.cpp
dejavu-pip-master/src/dejavu_gi/utility.h
src/dejavu_gi/__init__.py
src/dejavu_gi/bench.cpp
src/dejavu_gi/bench_iso.cpp
src/dejavu_gi/bfs.h
src/dejavu_gi/bijection.h
src/dejavu_gi.egg-info/PKG-INFO
src/dejavu_gi.egg-info/SOURCES.txt
src/dejavu_gi.egg-info/dependency_links.txt
src/dejavu_gi.egg-info/top_level.txt