Metadata-Version: 2.1
Name: dejavu-gi
Version: 0.1.2
Summary: ctypes bindings to graph isomorphism solver dejavu
Home-page: https://www.mathematik.tu-darmstadt.de/dejavu
Author: Markus Anders
Author-email: markus.anders@tu-darmstadt.de
License: UNKNOWN
Platform: UNKNOWN
Classifier: Programming Language :: Python :: 3
Classifier: License :: OSI Approved :: MIT License
Classifier: Operating System :: OS Independent
Requires-Python: >=3.6
